setup.py
BGD_probability/Binomialdistribution.py
BGD_probability/Gaussiandistribution.py
BGD_probability/Generaldistribution.py
BGD_probability/__init__.py
BGD_probability.egg-info/PKG-INFO
BGD_probability.egg-info/SOURCES.txt
BGD_probability.egg-info/dependency_links.txt
BGD_probability.egg-info/not-zip-safe
BGD_probability.egg-info/top_level.txt