Metadata-Version: 1.0
Name: BGD-probability
Version: 0.2
Summary: Gaussian and Binomial distributions
Home-page: UNKNOWN
Author: Nima Ghasemi
Author-email: nima.ghasemi@gmail.com
License: UNKNOWN
Platform: UNKNOWN
